line.py
line_counter-0.7.4.dist-info/DESCRIPTION.rst
line_counter-0.7.4.dist-info/METADATA
line_counter-0.7.4.dist-info/RECORD
line_counter-0.7.4.dist-info/WHEEL
line_counter-0.7.4.dist-info/entry_points.txt
line_counter-0.7.4.dist-info/metadata.json
line_counter-0.7.4.dist-info/top_level.txt
