Metadata-Version: 1.1
Name: line-counter
Version: 0.7.4
Summary: A command line tool to analyze the amount of lines and files under current directory.
Home-page: https://github.com/MorganZhang100/line-counter
Author: Morgan Zhang
Author-email: MorganZhang100@gmail.com
License: MIT
Keywords: file line code count
Platform: UNKNOWN
Classifier: Development Status :: 4 - Beta
Classifier: Environment :: Console
Classifier: Intended Audience :: Developers
Classifier: Topic :: Utilities
Classifier: License :: OSI Approved :: MIT License
Classifier: Programming Language :: Python :: 2
Classifier: Programming Language :: Python :: 3
